{"otherData": {},"traceEvents":[{"cat":"function","dur":320734,"name":"glfwInit","ph":"X","pid":0,"tid":4026640833,"ts":236235492094},{"cat":"function","dur":1577636,"name":"glfwCreateWindow","ph":"X","pid":0,"tid":4026640833,"ts":236235813245},{"cat":"function","dur":698,"name":"void __cdecl GammaEngine::OpenGLContext::Init(void)","ph":"X","pid":0,"tid":4026640833,"ts":236237390988},{"cat":"function","dur":22,"name":"void __cdecl GammaEngine::WindowsWindow::SetVSync(bool)","ph":"X","pid":0,"tid":4026640833,"ts":236237391746},{"cat":"function","dur":1899713,"name":"void __cdecl GammaEngine::WindowsWindow::Init(const struct GammaEngine::WindowProps &)","ph":"X","pid":0,"tid":4026640833,"ts":236235492093},{"cat":"function","dur":1899752,"name":"__cdecl GammaEngine::WindowsWindow::WindowsWindow(const struct GammaEngine::WindowProps &)","ph":"X","pid":0,"tid":4026640833,"ts":236235492087},{"cat":"function","dur":7,"name":"void __cdecl GammaEngine::OpenGLRendererAPI::Init(void)","ph":"X","pid":0,"tid":4026640833,"ts":236237391889},{"cat":"function","dur":10,"name":"__cdecl GammaEngine::OpenGLVertexArray::OpenGLVertexArray(void)","ph":"X","pid":0,"tid":4026640833,"ts":236237391941},{"cat":"function","dur":218396,"name":"__cdecl GammaEngine::OpenGLVertexBuffer::OpenGLVertexBuffer(unsigned int)","ph":"X","pid":0,"tid":4026640833,"ts":236237392033},{"cat":"function","dur":5,"name":"void __cdecl GammaEngine::OpenGLVertexBuffer::Bind(void) const","ph":"X","pid":0,"tid":4026640833,"ts":236237611181},{"cat":"function","dur":336,"name":"void __cdecl GammaEngine::OpenGLVertexArray::AddVertexBuffer(const class std::shared_ptr<class GammaEngine::VertexBuffer> &)","ph":"X","pid":0,"tid":4026640833,"ts":236237611164},{"cat":"function","dur":1367,"name":"__cdecl GammaEngine::OpenGLIndexBuffer::OpenGLIndexBuffer(unsigned int *,unsigned int)","ph":"X","pid":0,"tid":4026640833,"ts":236237614231},{"cat":"function","dur":1,"name":"void __cdecl GammaEngine::OpenGLIndexBuffer::Bind(void) const","ph":"X","pid":0,"tid":4026640833,"ts":236237615851},{"cat":"function","dur":92,"name":"void __cdecl GammaEngine::OpenGLVertexArray::SetIndexBuffer(const class std::shared_ptr<class GammaEngine::IndexBuffer> &)","ph":"X","pid":0,"tid":4026640833,"ts":236237615844},{"cat":"function","dur":470,"name":"__cdecl GammaEngine::OpenGLTexture2D::OpenGLTexture2D(unsigned int,unsigned int)","ph":"X","pid":0,"tid":4026640833,"ts":236237616032},{"cat":"function","dur":121,"name":"void __cdecl GammaEngine::OpenGLTexture2D::SetData(void *,unsigned int)","ph":"X","pid":0,"tid":4026640833,"ts":236237616569},{"cat":"function","dur":44,"name":"class std::unordered_map<unsigned int,class std::basic_string<char,struct std::char_traits<char>,class std::allocator<char> >,struct std::hash<unsigned int>,struct std::equal_to<unsigned int>,class std::allocator<struct std::pair<unsigned int const ,class std::basic_string<char,struct std::char_traits<char>,class std::allocator<char> > > > > __cdecl GammaEngine::OpenGLShader::PreProcess(const class std::basic_string<char,struct std::char_traits<char>,class std::allocator<char> > &)","ph":"X","pid":0,"tid":4026640833,"ts":236237636294}